datasetlib/__init__.py
datasetlib/datasets.py
datasetlib/datasets/amazon_reviews.csv
datasetlib/datasets/apple.csv
datasetlib/datasets/avocado.csv
datasetlib/datasets/babynames.csv
datasetlib/datasets/bank_client_information.csv
datasetlib/datasets/bmw.csv
datasetlib/datasets/canada_population.csv
datasetlib/datasets/cancer.csv
datasetlib/datasets/crypto_daily_prices.csv
datasetlib/datasets/crypto_daily_returns.csv
datasetlib/datasets/customer_complaints.csv
datasetlib/datasets/ecommerce_sales.csv
datasetlib/datasets/human_resources.csv
datasetlib/datasets/project1_sales_data.csv
datasetlib/datasets/project1_stores_data.csv
datasetlib/datasets/sp500_prices.csv
datasetlib/datasets/stock_daily_prices.csv
datasetlib/datasets/stocks.csv
datasetlib/datasets/summergames.csv
datasetlib/datasets/temperatures.csv
datasetlib/datasets/titanic.csv
datasetlib-0.2.6.dist-info/LICENSE
datasetlib-0.2.6.dist-info/METADATA
datasetlib-0.2.6.dist-info/WHEEL
datasetlib-0.2.6.dist-info/top_level.txt
datasetlib-0.2.6.dist-info/RECORD
