Metadata-Version: 2.1
Name: datasetlib
Version: 0.2.6
Summary: easy access to commonly used datasets in pandas dataframe format
Author-email: NeuralDevelopment <neutro2@outlook.de>
License: MIT License
Project-URL: Homepage, https://dev.azure.com/neuraldevelopment/datasetlib
Project-URL: Bug Tracker, https://dev.azure.com/neuraldevelopment/datasetlib/_backlogs/backlog/datasetlib%20Team/Epics
Classifier: License :: OSI Approved :: MIT License
Classifier: Operating System :: OS Independent
Classifier: Programming Language :: Python :: 3
Classifier: Programming Language :: Python :: 3.10
Classifier: Programming Language :: Python :: 3.11
Classifier: Programming Language :: Python :: 3.12
Requires-Python: >=3.10
License-File: LICENSE
Requires-Dist: basefunctions>=0.4.3
Requires-Dist: pandas>=2.0
